pyflowreg/__init__.py
pyflowreg/_runtime.py
pyflowreg/_version.py
pyflowreg/core/__init__.py
pyflowreg/core/backend_registry.py
pyflowreg/core/diso_optical_flow.py
pyflowreg/core/level_solver.py
pyflowreg/core/optical_flow.py
pyflowreg/core/warping.py
pyflowreg/cuda/__init__.py
pyflowreg/cuda/core/__init__.py
pyflowreg/cuda/core/level_solver.py
pyflowreg/cuda/util/__init__.py
pyflowreg/cuda/util/resize_util.py
pyflowreg/motion_correction/OF_options.py
pyflowreg/motion_correction/__init__.py
pyflowreg/motion_correction/compensate_arr.py
pyflowreg/motion_correction/compensate_recording.py
pyflowreg/motion_correction/flow_reg_live.py
pyflowreg/motion_correction/parallelization/__init__.py
pyflowreg/motion_correction/parallelization/base.py
pyflowreg/motion_correction/parallelization/multiprocessing.py
pyflowreg/motion_correction/parallelization/sequential.py
pyflowreg/motion_correction/parallelization/threading.py
pyflowreg/session/__init__.py
pyflowreg/session/cli.py
pyflowreg/session/config.py
pyflowreg/session/stage1_compensate.py
pyflowreg/session/stage2_between_avgs.py
pyflowreg/session/stage3_valid_mask.py
pyflowreg/torch/__init__.py
pyflowreg/torch/core/__init__.py
pyflowreg/torch/core/level_solver.py
pyflowreg/torch/util/__init__.py
pyflowreg/torch/util/resize_util.py
pyflowreg/util/__init__.py
pyflowreg/util/download.py
pyflowreg/util/image_processing.py
pyflowreg/util/resize_util.py
pyflowreg/util/superresolution_helpers.py
pyflowreg/util/visualization.py
pyflowreg/util/xcorr_prealignment.py
pyflowreg/util/io/__init__.py
pyflowreg/util/io/_arr.py
pyflowreg/util/io/_base.py
pyflowreg/util/io/_ds_io.py
pyflowreg/util/io/_null.py
pyflowreg/util/io/_scanimage.py
pyflowreg/util/io/factory.py
pyflowreg/util/io/hdf5.py
pyflowreg/util/io/mat.py
pyflowreg/util/io/mdf.py
pyflowreg/util/io/multifile_wrappers.py
pyflowreg/util/io/tiff.py
pyflowreg-0.1.0a7.dist-info/METADATA
pyflowreg-0.1.0a7.dist-info/WHEEL
pyflowreg-0.1.0a7.dist-info/entry_points.txt
pyflowreg-0.1.0a7.dist-info/top_level.txt
pyflowreg-0.1.0a7.dist-info/RECORD
