Metadata-Version: 2.4
Name: pyflowreg
Version: 0.1.0a7
Summary: Variational optical-flow motion correction for 2-photon microscopy videos and 3D scans
Author-email: Philipp Flotho <Philipp.Flotho@uni-saarland.de>
License: CC BY-NC-SA 4.0
Classifier: Development Status :: 3 - Alpha
Classifier: Intended Audience :: Science/Research
Classifier: License :: Other/Proprietary License
Classifier: Operating System :: OS Independent
Classifier: Programming Language :: Python :: 3
Classifier: Programming Language :: Python :: 3.10
Classifier: Programming Language :: Python :: 3.11
Classifier: Programming Language :: Python :: 3.12
Classifier: Programming Language :: Python :: 3.13
Classifier: Topic :: Scientific/Engineering :: Image Processing
Classifier: Topic :: Scientific/Engineering :: Bio-Informatics
Requires-Python: >=3.10
Requires-Dist: numpy>=2.0.0
Requires-Dist: scipy>=1.14.0
Requires-Dist: scikit-image>=0.24.0
Requires-Dist: opencv-contrib-python>=4.10.0
Requires-Dist: h5py>=3.12.0
Requires-Dist: tifffile>=2024.9.0
Requires-Dist: numba>=0.60.0
Requires-Dist: pydantic<3.0.0,>=2.11.0
Requires-Dist: hdf5storage>=0.2.0
Requires-Dist: pywin32>=311; platform_system == "Windows"
Provides-Extra: vis
Requires-Dist: matplotlib>=3.8.0; extra == "vis"
Requires-Dist: scikit-learn>=1.5.0; extra == "vis"
Provides-Extra: session
Requires-Dist: pyyaml>=6.0; extra == "session"
Requires-Dist: Pillow>=10.0; extra == "session"
Provides-Extra: dask
Requires-Dist: dask[distributed]>=2024.0.0; extra == "dask"
Requires-Dist: dask-jobqueue>=0.8.0; extra == "dask"
Provides-Extra: test
Requires-Dist: pytest>=8.0.0; extra == "test"
Requires-Dist: pytest-cov>=5.0.0; extra == "test"
Provides-Extra: gpu
Requires-Dist: cupy-cuda12x; (platform_system == "Linux" or platform_system == "Windows") and extra == "gpu"
Requires-Dist: torch>=2.2.0; extra == "gpu"
Provides-Extra: docs
Requires-Dist: sphinx~=7.3; extra == "docs"
Requires-Dist: myst-parser~=4.0; extra == "docs"
Requires-Dist: linkify-it-py~=2.0; extra == "docs"
Requires-Dist: sphinx-copybutton~=0.5; extra == "docs"
Requires-Dist: sphinx-design~=0.6; extra == "docs"
Requires-Dist: sphinxcontrib-bibtex~=2.6; extra == "docs"
Requires-Dist: pydata-sphinx-theme~=0.15; extra == "docs"
Requires-Dist: sphinx-autodoc-typehints~=2.0; extra == "docs"
